<?xml version="1.0" encoding="utf-8"?>
<search>
  
  
  
  <entry>
    <title>MATH 407: Probability Theory</title>
    <link href="/2022/12/02/MATH407/"/>
    <url>/2022/12/02/MATH407/</url>
    
    <content type="html"><![CDATA[<link rel="stylesheet" class="aplayer-secondary-style-marker" href="/assets/css/APlayer.min.css"><script src="/assets/js/APlayer.min.js" class="aplayer-secondary-script-marker"></script><h1 id="Description"><a href="#Description" class="headerlink" title="Description"></a>Description</h1><ul><li>Intructor: Dr. Sergey Lototsky</li><li>Objective: To learn the basics of probability so that you are prepared for statistics (math 408). Some particular topics to master are (a) Law of Large Numbers (LLN) (b) Central Limit Theorem (CLT) (c) Normal (Gaussian) distribution (d) Poisson approximation.</li></ul><p>I did not attend all the lectures (in fact, never go to lectures), thus don’t have a complete set of notes. I will try to fill in the gaps as I go along. However, I do have the Computer Project for this course, feel free to check it out.</p><h1 id="Syllabus"><a href="#Syllabus" class="headerlink" title="Syllabus"></a>Syllabus</h1><p>If you could not preview, download here: <a href="/img/MATH407/pdf/MATH407_Syllabus.pdf">MATH407_Syllabus.pdf</a></p><div class="row">    <embed src="/img/MATH407/pdf/MATH407_Syllabus.pdf" width="100%" height="550" type="application/pdf"></div><h1 id="Computer-Project"><a href="#Computer-Project" class="headerlink" title="Computer Project"></a>Computer Project</h1><p>If you could not preview, download here: <a href="/img/MATH07/pdf/MATH407_CP.pdf">MATH407_Notes.pdf</a></p><div class="row">    <embed src="/img/MATH407/pdf/MATH407_CP.pdf" width="100%" height="550" type="application/pdf"></div>]]></content>
    
    
    <categories>
      
      <category>Notes</category>
      
      <category>2022 Fall</category>
      
    </categories>
    
    
    <tags>
      
      <tag>MATH</tag>
      
      <tag>Notes</tag>
      
      <tag>MATH407</tag>
      
      <tag>2022 Fall</tag>
      
    </tags>
    
  </entry>
  
  
  
  <entry>
    <title>MATH 430: Thoery of Numbers</title>
    <link href="/2022/12/02/MATH430/"/>
    <url>/2022/12/02/MATH430/</url>
    
    <content type="html"><![CDATA[<link rel="stylesheet" class="aplayer-secondary-style-marker" href="/assets/css/APlayer.min.css"><script src="/assets/js/APlayer.min.js" class="aplayer-secondary-script-marker"></script><h1 id="Description"><a href="#Description" class="headerlink" title="Description"></a>Description</h1><ul><li>Intructor: Masoud Zargar</li><li>Course description: This is a course on (elementary) number theory, covering the basic problems with which this subject deals, as well as how it is related to other areas of mathematics. Throughout the course, I will also inspire some abstract mathematics that has been developed to generalize some related classical concepts. We will try to follow the first 9 chapters of the textbook, with some deviations into analytic number theory and very basic abstract algebra.</li></ul><h1 id="Syllabus"><a href="#Syllabus" class="headerlink" title="Syllabus"></a>Syllabus</h1><p>If you could not preview, download here: <a href="/img/MATH430/pdf/MATH430_Syllabus.pdf">MATH430_Syllabus.pdf</a></p><div class="row">    <embed src="/img/MATH430/pdf/MATH430_Syllabus.pdf" width="100%" height="550" type="application/pdf"></div><h1 id="Personal-Comments"><a href="#Personal-Comments" class="headerlink" title="Personal Comments"></a>Personal Comments</h1><p>MATH430, especially instructed by Professor Zargar, is an excellent proof-based course for beginners. However, Professor Zargar does not “curve up” on the exams; during the 2022 Fall semester, he <strong>curved down</strong> the grade. Specifically, you need to get approximately 97% on the final grade to get an A, which is intended to have 4 out of 40 students get an A (though it does not affect my grade). Thus, be prepared to take notes, <strong>do bonus problems</strong> on the homework, and try to understand the proofs and materials. You will learn much if you put in the effort, and I highly recommend the course.</p><h1 id="Note"><a href="#Note" class="headerlink" title="Note"></a>Note</h1><p>If you could not preview, download here: <a href="/img/MATH430/pdf/MATH430_Notes.pdf">MATH430_Notes.pdf</a></p><div class="row">    <embed src="/img/MATH430/pdf/MATH430_Notes.pdf" width="100%" height="550" type="application/pdf"></div>]]></content>
    
    
    <categories>
      
      <category>Notes</category>
      
      <category>2022 Fall</category>
      
    </categories>
    
    
    <tags>
      
      <tag>MATH</tag>
      
      <tag>Notes</tag>
      
      <tag>2022 Fall</tag>
      
      <tag>MATH430</tag>
      
    </tags>
    
  </entry>
  
  
  
  <entry>
    <title>MATH 226: Calculus III</title>
    <link href="/2022/10/22/MATH226/"/>
    <url>/2022/10/22/MATH226/</url>
    
    <content type="html"><![CDATA[<link rel="stylesheet" class="aplayer-secondary-style-marker" href="/assets/css/APlayer.min.css"><script src="/assets/js/APlayer.min.js" class="aplayer-secondary-script-marker"></script><h1 id="Description"><a href="#Description" class="headerlink" title="Description"></a>Description</h1><ul><li>Intructor: Dr. Guillaume Dreyer</li><li>Course Coentent: space curve, surface, curvature, function of several variables, partial derivatives, multiple integral, line integral, surface integral, Stokes’ Theorem and its ap- plications.</li></ul><p>MATH 226: Calculus III by Prof. Guillaume Dreyer is indeed hard in some extend, but what you need to do is just practice and practice. Read the books and notes, and do <em>all the past exams</em>. You will be fine.</p><h1 id="Syllabus"><a href="#Syllabus" class="headerlink" title="Syllabus"></a>Syllabus</h1><p>If you could not preview, download here: <a href="/img/MATH226/pdf/MATH226_Syllabus.pdf">MATH226_Syllabus.pdf</a></p><div class="row">    <embed src="/img/MATH226/pdf/MATH226_Syllabus.pdf" width="100%" height="550" type="application/pdf"></div><h1 id="Notes"><a href="#Notes" class="headerlink" title="Notes"></a>Notes</h1><p>If you could not preview, download here: <a href="/img/MATH226/pdf/MATH226_Notes.pdf">MATH226_Notes.pdf</a></p><div class="row">    <embed src="/img/MATH226/pdf/MATH226_Notes.pdf" width="100%" height="550" type="application/pdf"></div>]]></content>
    
    
    <categories>
      
      <category>Notes</category>
      
      <category>2022 Spring</category>
      
    </categories>
    
    
    <tags>
      
      <tag>MATH226</tag>
      
      <tag>MATH</tag>
      
      <tag>2022 Spring</tag>
      
      <tag>Notes</tag>
      
    </tags>
    
  </entry>
  
  
  
  
</search>
